DAHU/.idea/.gitignore
DAHU/.idea/DAHU.iml
DAHU/.idea/inspectionProfiles/profiles_settings.xml
DAHU/.idea/misc.xml
DAHU/.idea/modules.xml
DAHU/.idea/vcs.xml
DAHU/__init__.py
DAHU/cartes.py
DAHU/chimie.py
DAHU/donnees.py
DAHU/elec.py
DAHU/erreurs.py
DAHU/graph.py
DAHU/main.py
DAHU/maths.py
DAHU/meca.py
DAHU/papiers.py
DAHU/phy.py
DAHU/test.py
dahu12-0.0.0.0.2.2.dist-info/LICENSE
dahu12-0.0.0.0.2.2.dist-info/METADATA
dahu12-0.0.0.0.2.2.dist-info/WHEEL
dahu12-0.0.0.0.2.2.dist-info/RECORD
