Metadata-Version: 2.1
Name: dahu12
Version: 0.0.0.0.2.2
Summary: Package de calcul formel (pour l'instant ;=) )
Home-page: https://github.com/MoiCAntho/DAHU
License: MIT
Author: LOUVAT SEGURA Anthony
Requires-Python: >=3.7,<4.0
Classifier: License :: OSI Approved :: MIT License
Classifier: Programming Language :: Python :: 3
Classifier: Programming Language :: Python :: 3.7
Classifier: Programming Language :: Python :: 3.8
Classifier: Programming Language :: Python :: 3.9
Classifier: Programming Language :: Python :: 3.10
Classifier: Programming Language :: Python :: 3.11
Requires-Dist: cython (>=0.29.35,<0.30.0)
Requires-Dist: giacpy (>=0.7.1,<0.8.0)
Requires-Dist: wheel (>=0.40.0,<0.41.0)
Project-URL: Bug Tracker, https://github.com/MoiCAntho/DAHU/issues
Project-URL: Repository, https://github.com/MoiCAntho/DAHU
